thalesians/__init__.py
thalesians/adiutor/__init__.py
thalesians/adiutor/checks.py
thalesians/adiutor/conditions.py
thalesians/adiutor/config.py
thalesians/adiutor/conversions.py
thalesians/adiutor/exceptions.py
thalesians/adiutor/intervals.py
thalesians/adiutor/jupyter_utils.py
thalesians/adiutor/latex_utils.py
thalesians/adiutor/number_theory.py
thalesians/adiutor/numpy_checks.py
thalesians/adiutor/numpy_utils.py
thalesians/adiutor/objects.py
thalesians/adiutor/pandas_utils.py
thalesians/adiutor/python_utils.py
thalesians/adiutor/randomness.py
thalesians/adiutor/strings.py
thalesians/adiutor/system_utils.py
thalesians/adiutor/time_consts.py
thalesians/adiutor/timer.py
thalesians/adiutor/times.py
thalesians/adiutor/utils.py
thalesians/adiutor/visual.py
thalesians/adiutor/stats/__init__.py
thalesians/adiutor/stats/calculators.py
thalesians.adiutor-0.0.4.dist-info/LICENSE
thalesians.adiutor-0.0.4.dist-info/METADATA
thalesians.adiutor-0.0.4.dist-info/WHEEL
thalesians.adiutor-0.0.4.dist-info/top_level.txt
thalesians.adiutor-0.0.4.dist-info/RECORD
