Metadata-Version: 2.1
Name: thalesians.adiutor
Version: 0.0.4
Summary: A collection of general-purpose Python utilities designed for reuse across multiple projects
Author-email: Paul Alexander Bilokon <paul@thalesians.com>, Abir Sridi <abir.sridi@thalesians.com>
Project-URL: Homepage, https://github.com/thalesians/adiutor/
Project-URL: Issues, https://github.com/thalesians/adiutor/issues
Classifier: Programming Language :: Python :: 3
Classifier: License :: OSI Approved :: Apache Software License
Classifier: Operating System :: OS Independent
Requires-Python: >=3.12
License-File: LICENSE
Requires-Dist: numpy>=1.26.4
Requires-Dist: pytz>=2024.2
Requires-Dist: unidecode>=1.3.8
Requires-Dist: pandas>=2.2.3
Requires-Dist: scipy>=1.14.1
Requires-Dist: sympy>=1.13.3
Requires-Dist: jinja2>=3.1.4
